topo_descriptors/__init__.py
topo_descriptors/helpers.py
topo_descriptors/topo.py
topo_descriptors/config/topo_descriptors.conf
topo_descriptors-0.5.0.dist-info/AUTHORS.rst
topo_descriptors-0.5.0.dist-info/LICENSE
topo_descriptors-0.5.0.dist-info/METADATA
topo_descriptors-0.5.0.dist-info/WHEEL
topo_descriptors-0.5.0.dist-info/top_level.txt
topo_descriptors-0.5.0.dist-info/RECORD
