Metadata-Version: 2.1
Name: topo-descriptors
Version: 0.5.0
Summary: A library to compute DEM-based topographical descriptors.
Home-page: https://github.com/MeteoSwiss/topo-descriptors
Author: Mathieu Schaer
Author-email: mathieu.schaer@meteoswiss.ch
Maintainer: Daniele Nerini
Maintainer-email: daniele.nerini@meteoswiss.ch
License: BSD-3-Clause license
Keywords: topo_descriptors
Classifier: Development Status :: 3 - Alpha
Classifier: Intended Audience :: Developers
Classifier: Intended Audience :: Science/Research
Classifier: License :: OSI Approved :: BSD License
Classifier: Natural Language :: English
Classifier: Programming Language :: Python :: 3.8
Classifier: Programming Language :: Python :: 3.9
Classifier: Programming Language :: Python :: 3.10
Classifier: Topic :: Scientific/Engineering
Classifier: Operating System :: OS Independent
License-File: LICENSE
License-File: AUTHORS.rst
Requires-Dist: netcdf4
Requires-Dist: numba
Requires-Dist: dask
Requires-Dist: numpy
Requires-Dist: pandas
Requires-Dist: scipy
Requires-Dist: utm
Requires-Dist: xarray
Requires-Dist: yaconfigobject
Provides-Extra: test
Requires-Dist: pytest ; extra == 'test'
